slz/__init__.py
slz/version.py
slz/slz.cpython-35m-x86_64-linux-gnu.so
slz-0.0.1.0.dist-info/RECORD
slz-0.0.1.0.dist-info/METADATA
slz-0.0.1.0.dist-info/top_level.txt
slz-0.0.1.0.dist-info/LICENSE
slz-0.0.1.0.dist-info/WHEEL
